Metadata-Version: 2.1
Name: cellsnake
Version: 0.2.0.12rc2
Summary: cellsnake
Home-page: https://github.com/sinanugur/cellsnake
Author: Sinan U. Umu
Author-email: sinanugur@gmail.com
Keywords: scRNA single-cell RNA analysis
Classifier: License :: OSI Approved :: MIT License
Classifier: Programming Language :: Python :: 3
Classifier: Topic :: Scientific/Engineering :: Bio-Informatics
License-File: LICENSE
Requires-Dist: scipy>=1.6.2
Requires-Dist: regex>=2021.4.4
Requires-Dist: pysam>=0.16.0.1
Requires-Dist: matplotlib<3.7
Requires-Dist: celltypist==1.3.0
Requires-Dist: pandas
Requires-Dist: fuzzywuzzy
Requires-Dist: snakemake>=7.22.0
Requires-Dist: levenshtein
Requires-Dist: docopt
Requires-Dist: umap-learn
Requires-Dist: plotly
Requires-Dist: kaleido
